{
  "_comment_info": "這裡是 各地區中文名稱 與 相對應之變數名稱 的對照表，各 js 都會讀取本檔案，並以本內容為依據。",
  "_comment_author": "有問題請聯絡 johnyluyte@gmail.com",
  "_comment_example":[
    {
      "id": "就是id，基本上不要動：（22）",
      "name": "地區之中文名稱，會出現在選志願的選單：（花蓮縣環保局）",
      "homeName": "地區的戶籍地名稱，會出現在選戶籍地的選單：（花蓮縣）",
      "shortName": "地區之簡稱，會出現在預排結果的表格：（花蓮）",
      "available": "地區之役男開放名額：（2）"
    }
  ],
  "regionLists": [
    {
      "id": 0,
      "name": "本署",
      "homeName": "本署",
      "shortName": "本署",
      "available": 3
    },
    {
      "id": 1,
      "name": "環訓所",
      "homeName": "環訓所",
      "shortName": "環訓",
      "available": 1
    },
    {
      "id": 2,
      "name": "環檢驗所",
      "homeName": "環檢所",
      "shortName": "環檢",
      "available": 2
    },
    {
      "id": 3,
      "name": "警政署環保警察隊",
      "homeName": "環警",
      "shortName": "環警",
      "available": 0
    },
    {
      "id": 4,
      "name": "基隆市環保局",
      "homeName": "基隆市",
      "shortName": "基隆",
      "available": 1
    },
    {
      "id": 5,
      "name": "台北市政府環保局",
      "homeName": "臺北市",
      "shortName": "台北",
      "available": 2
    },
    {
      "id": 6,
      "name": "新北市政府環保局",
      "homeName": "新北市",
      "shortName": "新北",
      "available": 5
    },
    {
      "id": 7,
      "name": "桃園縣政府環保局",
      "homeName": "桃園縣",
      "shortName": "桃園",
      "available": 4
    },
    {
      "id": 8,
      "name": "新竹市環保局",
      "homeName": "新竹市",
      "shortName": "竹市",
      "available": 3
    },
    {
      "id": 9,
      "name": "新竹縣政府環保局",
      "homeName": "新竹縣",
      "shortName": "竹縣",
      "available": 2
    },
    {
      "id": 10,
      "name": "苗栗縣政府環保局",
      "homeName": "苗栗縣",
      "shortName": "苗栗",
      "available": 2
    },
    {
      "id": 11,
      "name": "台中市政府環保局",
      "homeName": "臺中市",
      "shortName": "台中",
      "available": 3
    },
    {
      "id": 12,
      "name": "彰化縣環保局",
      "homeName": "彰化縣",
      "shortName": "彰化",
      "available": 4
    },
    {
      "id": 13,
      "name": "南投縣政府環保局",
      "homeName": "南投縣",
      "shortName": "南投",
      "available": 3
    },
    {
      "id": 14,
      "name": "雲林縣環保局",
      "homeName": "雲林縣",
      "shortName": "雲林",
      "available": 4
    },
    {
      "id": 15,
      "name": "嘉義市環境保護局",
      "homeName": "嘉義市",
      "shortName": "嘉市",
      "available": 0
    },
    {
      "id": 16,
      "name": "嘉義縣環保局",
      "homeName": "嘉義縣",
      "shortName": "嘉縣",
      "available": 1
    },
    {
      "id": 17,
      "name": "台南市政府環保局",
      "homeName": "臺南市",
      "shortName": "台南",
      "available": 2
    },
    {
      "id": 18,
      "name": "高雄市政府環保局",
      "homeName": "高雄市",
      "shortName": "高市",
      "available": 2
    },
    {
      "id": 19,
      "name": "高雄市政府海洋局",
      "homeName": "高雄市",
      "_comment_homeName": "這裡使用高雄市是因為：高雄市戶籍的人也可以優先選高雄海洋局。",
      "shortName": "高海",
      "available": 1
    },
    {
      "id": 20,
      "name": "屏東縣環保局",
      "homeName": "屏東縣",
      "shortName": "屏東",
      "available": 1
    },
    {
      "id": 21,
      "name": "宜蘭縣政府環保局",
      "homeName": "宜蘭縣",
      "shortName": "宜蘭",
      "available": 2
    },
    {
      "id": 22,
      "name": "花蓮縣環保局",
      "homeName": "花蓮縣",
      "shortName": "花蓮",
      "available": 1
    },
    {
      "id": 23,
      "name": "台東縣環保局",
      "homeName": "台東縣",
      "shortName": "台東",
      "available": 1
    },
    {
      "id": 24,
      "name": "澎湖縣政府環保局",
      "homeName": "澎湖縣",
      "shortName": "澎湖",
      "available": 1
    },
    {
      "id": 25,
      "name": "連江縣政府環保局",
      "homeName": "連江縣",
      "shortName": "連江",
      "available": 0
    }
  ]
}